django_components_preprocessor/__init__.py
django_components_preprocessor/loader.py
django_components_preprocessor-0.3.0.dist-info/LICENSE
django_components_preprocessor-0.3.0.dist-info/WHEEL
django_components_preprocessor-0.3.0.dist-info/METADATA
django_components_preprocessor-0.3.0.dist-info/RECORD
